Workbook

Sheet Dashboard
A1: Sales Performance & Customer Insights Dashboard
A3: Data Source: Dataset (200 orders, FY2024) | Use filters below to slice by Region and Product Category
A4: Region Filter | B4: All | D4: Product Category Filter | F4: All | H4: Filtered Sales: | I4: =SUMPRODUCT(((Dataset!$C$2:$C$201=IF($B$4="All",Dataset!$C$2:$C$201,$B$4)))*((Dataset!$B$2:$B$201=IF($F$4="All",Dataset!$B$2:$B$201,$F$4)))*(Dataset!$E$2:$E$201)) -> 529594.51
A6: Total Sales ($) | D6: Total Profit ($) | G6: Profit Margin % | J6: Total Quantity Sold
A7: =SUM(Dataset!E2:E201) -> 529594.51 | D7: =SUM(Dataset!F2:F201) -> 111759.97 | G7: =SUM(Dataset!F2:F201)/SUM(Dataset!E2:E201) -> 0.21102932 | J7: =SUM(Dataset!G2:G201) -> 2351
A9: Chart Data (linked to Dataset)
A10: Month | B10: Sales | D10: Region | E10: Sales | G10: Category | H10: Profit | J10: Segment | K10: Sales
A11: Jan | B11: =SUMPRODUCT((MONTH(Dataset!$A$2:$A$201)=1)*(Dataset!$E$2:$E$201)) -> 14727.98 | D11: North | E11: =SUMIF(Dataset!$C$2:$C$201,$D11,Dataset!$E$2:$E$201) -> 149083.04 | G11: Electronics | H11: =SUMIF(Dataset!$B$2:$B$201,$G11,Dataset!$F$2:$F$201) -> 39124.69 | J11: Consumer | K11: =SUMIF(Dataset!$D$2:$D$201,$J11,Dataset!$E$2:$E$201) -> 141741.76
A12: Feb | B12: =SUMPRODUCT((MONTH(Dataset!$A$2:$A$201)=2)*(Dataset!$E$2:$E$201)) -> 23194.83 | D12: South | E12: =SUMIF(Dataset!$C$2:$C$201,$D12,Dataset!$E$2:$E$201) -> 100897.41 | G12: Furniture | H12: =SUMIF(Dataset!$B$2:$B$201,$G12,Dataset!$F$2:$F$201) -> 51768.34 | J12: Corporate | K12: =SUMIF(Dataset!$D$2:$D$201,$J12,Dataset!$E$2:$E$201) -> 177815.13
A13: Mar | B13: =SUMPRODUCT((MONTH(Dataset!$A$2:$A$201)=3)*(Dataset!$E$2:$E$201)) -> 49868.36 | D13: East | E13: =SUMIF(Dataset!$C$2:$C$201,$D13,Dataset!$E$2:$E$201) -> 138952.76 | G13: Clothing | H13: =SUMIF(Dataset!$B$2:$B$201,$G13,Dataset!$F$2:$F$201) -> 12029.38 | J13: Small Business | K13: =SUMIF(Dataset!$D$2:$D$201,$J13,Dataset!$E$2:$E$201) -> 210037.62
A14: Apr | B14: =SUMPRODUCT((MONTH(Dataset!$A$2:$A$201)=4)*(Dataset!$E$2:$E$201)) -> 21135.41 | D14: West | E14: =SUMIF(Dataset!$C$2:$C$201,$D14,Dataset!$E$2:$E$201) -> 140661.3 | G14: Office Supplies | H14: =SUMIF(Dataset!$B$2:$B$201,$G14,Dataset!$F$2:$F$201) -> 6946.88
A15: May | B15: =SUMPRODUCT((MONTH(Dataset!$A$2:$A$201)=5)*(Dataset!$E$2:$E$201)) -> 79653.04 | G15: Groceries | H15: =SUMIF(Dataset!$B$2:$B$201,$G15,Dataset!$F$2:$F$201) -> 1890.68
A16: Jun | B16: =SUMPRODUCT((MONTH(Dataset!$A$2:$A$201)=6)*(Dataset!$E$2:$E$201)) -> 51474.2
A17: Jul | B17: =SUMPRODUCT((MONTH(Dataset!$A$2:$A$201)=7)*(Dataset!$E$2:$E$201)) -> 43176.75
A18: Aug | B18: =SUMPRODUCT((MONTH(Dataset!$A$2:$A$201)=8)*(Dataset!$E$2:$E$201)) -> 70477.34
A19: Sep | B19: =SUMPRODUCT((MONTH(Dataset!$A$2:$A$201)=9)*(Dataset!$E$2:$E$201)) -> 55339.26
A20: Oct | B20: =SUMPRODUCT((MONTH(Dataset!$A$2:$A$201)=10)*(Dataset!$E$2:$E$201)) -> 15568.29
A21: Nov | B21: =SUMPRODUCT((MONTH(Dataset!$A$2:$A$201)=11)*(Dataset!$E$2:$E$201)) -> 64241.59
A22: Dec | B22: =SUMPRODUCT((MONTH(Dataset!$A$2:$A$201)=12)*(Dataset!$E$2:$E$201)) -> 40737.46

Sheet Business Case
A1: Sales Performance & Customer Insights Dashboard
A4: Company
A5: BrightMart Retail Co. is a mid-sized multi-category retailer selling Electronics, Furniture, Clothing, Office Supplies, and Groceries across four U.S. regions to Consumer, Corporate, and Small Business customers.
A7: Business Problem
A8: Sales and profit data are recorded transaction-by-transaction but never summarized. Leadership cannot easily tell which regions, categories, or customer segments are actually profitable, so budget and marketing decisions are made without clear evidence.
A10: Objective
A11: Build a simple, interactive Excel dashboard that tracks total sales, profit, and quantity sold, and lets managers filter by region and product category to quickly spot top and underperforming segments.

Sheet Dataset
A1: Order Date | B1: Product Category | C1: Region | D1: Customer Segment | E1: Sales Amount | F1: Profit | G1: Quantity Sold
A2: 45457 | B2: Furniture | C2: West | D2: Small Business | E2: 301.42 | F2: 69.04 | G2: 2
A3: 45479 | B3: Groceries | C3: North | D3: Small Business | E3: 54.67 | F3: 6.53 | G3: 7
A4: 45327 | B4: Furniture | C4: North | D4: Small Business | E4: 1979.32 | F4: 459.16 | G4: 14
A5: 45406 | B5: Groceries | C5: North | D5: Small Business | E5: 660.25 | F5: 98.19 | G5: 19
A6: 45315 | B6: Groceries | C6: South | D6: Corporate | E6: 221.48 | F6: 22.67 | G6: 14
A7: 45449 | B7: Groceries | C7: South | D7: Consumer | E7: 908.96 | F7: 96.48 | G7: 19
A8: 45341 | B8: Groceries | C8: North | D8: Small Business | E8: 102.86 | F8: 12.63 | G8: 2
A9: 45564 | B9: Office Supplies | C9: East | D9: Corporate | E9: 2120.02 | F9: 571.47 | G9: 19
A10: 45419 | B10: Furniture | C10: South | D10: Consumer | E10: 5893.23 | F10: 1326.07 | G10: 19
A11: 45467 | B11: Office Supplies | C11: East | D11: Small Business | E11: 68.97 | F11: 19.08 | G11: 3
A12: 45467 | B12: Furniture | C12: West | D12: Corporate | E12: 1546.82 | F12: 284.13 | G12: 2
A13: 45577 | B13: Groceries | C13: East | D13: Corporate | E13: 718.98 | F13: 88.31 | G13: 23
... A201: 45426 | B201: Electronics | C201: East | D201: Small Business | E201: 7797.6 | F201: 1555.97 | G201: 18

Sheet Lists
A1: All | B1: All
A2: North | B2: Electronics
A3: South | B3: Furniture
A4: East | B4: Clothing
A5: West | B5: Office Supplies
B6: Groceries

Sheet Key Insights
A1: Key Insights
A4: 1 | B4: Electronics and Furniture generate the highest average order value, but Groceries has the lowest profit margin of all categories, dragging down overall profitability despite steady sales volume.
A7: 2 | B7: The West and North regions post the strongest total sales, while the South region lags noticeably behind the other three, suggesting an untapped growth opportunity or a regional demand issue.
A10: 3 | B10: Corporate customers place fewer orders than Consumer customers but tend to buy in larger quantities per order, making them a high-value segment worth targeted retention efforts.
A13: 4 | B13: Monthly sales show clear seasonal peaks, with noticeably higher activity in certain months, indicating that inventory and staffing could be planned around these predictable demand swings.

Sheet Recommendations
A1: Recommendations
A4: 1 | B4: Review pricing and supplier costs for Groceries to improve its margin, since volume alone is not translating into meaningful profit.
A7: 2 | B7: Investigate the South region's underperformance with a local sales or marketing push, and compare its store/staffing setup against the stronger-performing regions.
A10: 3 | B10: Build a loyalty or volume-discount program for Corporate customers to protect and grow this high-value, high-quantity segment.
A13: 4 | B13: Use the identified seasonal sales peaks to plan inventory restocking and staffing levels a month ahead, reducing stockouts during high-demand periods.
